setup.py
frasco_twitter/__init__.py
frasco_twitter/blueprint.py
frasco_twitter.egg-info/PKG-INFO
frasco_twitter.egg-info/SOURCES.txt
frasco_twitter.egg-info/dependency_links.txt
frasco_twitter.egg-info/not-zip-safe
frasco_twitter.egg-info/requires.txt
frasco_twitter.egg-info/top_level.txt