Metadata-Version: 1.0
Name: frasco-twitter
Version: 0.1
Summary: Twitter integration for Frasco
Home-page: http://github.com/frascoweb/frasco-twitter
Author: Maxime Bouroumeau-Fuseau
Author-email: maxime.bouroumeau@gmail.com
License: MIT
Platform: any
